LICENSE
README.md
setup.py
varorm/__init__.py
varorm/exceptions.py
varorm/fields.py
varorm/models.py
varorm/storage.py
varorm.egg-info/PKG-INFO
varorm.egg-info/SOURCES.txt
varorm.egg-info/dependency_links.txt
varorm.egg-info/top_level.txt
varorm/dj/__init__.py
varorm/dj/admin.py
varorm/dj/apps.py
varorm/dj/foms.py
varorm/dj/globals.py
varorm/dj/loader.py
varorm/dj/models.py
varorm/dj/utils.py
varorm/dj/views.py
varorm/dj/migrations/0001_initial.py
varorm/dj/migrations/__init__.py
varorm/dj/templates/models_list.html